<links>
    <link domain="www.worldometers.info">https://www.worldometers.info/population/europe/eastern-europe/</link>
    <link domain="www.worldometers.info">https://www.worldometers.info/demographics/russia-demographics/</link>
    <link domain="www.worldometers.info">https://www.worldometers.info/demographics/russia-demographics/#life-exp</link>
    <link domain="www.worldometers.info">https://www.worldometers.info/demographics/russia-demographics/#u5-infa-title</link>
    <link domain="www.worldometers.info">https://www.worldometers.info/demographics/russia-demographics/#median-age</link>
    <link domain="www.worldometers.info">https://www.worldometers.info/demographics/russia-demographics/#tfr</link>
    <link domain="www.worldometers.info">https://www.worldometers.info/demographics/russia-demographics/#urb</link>
    <link domain="www.worldometers.info">https://www.worldometers.info/gdp/russia-gdp/</link>
</links>